LICENSE
MANIFEST.in
README.rst
setup.py
src/zumanji/__init__.py
src/zumanji/admin.py
src/zumanji/forms.py
src/zumanji/github.py
src/zumanji/helpers.py
src/zumanji/importer.py
src/zumanji/models.py
src/zumanji/urls.py
src/zumanji/views.py
src/zumanji.egg-info/PKG-INFO
src/zumanji.egg-info/SOURCES.txt
src/zumanji.egg-info/dependency_links.txt
src/zumanji.egg-info/not-zip-safe
src/zumanji.egg-info/requires.txt
src/zumanji.egg-info/top_level.txt
src/zumanji/interfaces/__init__.py
src/zumanji/interfaces/base.py
src/zumanji/interfaces/cache.py
src/zumanji/interfaces/redis.py
src/zumanji/interfaces/sql.py
src/zumanji/management/__init__.py
src/zumanji/management/commands/__init__.py
src/zumanji/management/commands/import_performance_json.py
src/zumanji/management/commands/poll_github.py
src/zumanji/migrations/0001_initial.py
src/zumanji/migrations/0002_auto__add_unique_project_label.py
src/zumanji/migrations/0003_auto__add_field_revision_datetime__add_field_revision_parent.py
src/zumanji/migrations/__init__.py
src/zumanji/static/zumanji/.DS_Store
src/zumanji/static/zumanji/css/bootstrap-responsive.css
src/zumanji/static/zumanji/css/bootstrap-responsive.min.css
src/zumanji/static/zumanji/css/bootstrap.css
src/zumanji/static/zumanji/css/bootstrap.min.css
src/zumanji/static/zumanji/css/zumanji.css
src/zumanji/static/zumanji/img/glyphicons-halflings-white.png
src/zumanji/static/zumanji/img/glyphicons-halflings.png
src/zumanji/static/zumanji/js/bootstrap.js
src/zumanji/static/zumanji/js/bootstrap.min.js
src/zumanji/static/zumanji/js/jquery-1.8.0.js
src/zumanji/static/zumanji/js/jquery-1.8.0.min.js
src/zumanji/static/zumanji/js/jquery.sparkline.js
src/zumanji/static/zumanji/js/jquery.sparkline.min.js
src/zumanji/static/zumanji/js/zumanji.js
src/zumanji/templates/zumanji/build.html
src/zumanji/templates/zumanji/index.html
src/zumanji/templates/zumanji/layout.html
src/zumanji/templates/zumanji/project.html
src/zumanji/templates/zumanji/tag.html
src/zumanji/templates/zumanji/test.html
src/zumanji/templates/zumanji/upload_build.html
src/zumanji/templates/zumanji/includes/build_details.html
src/zumanji/templates/zumanji/includes/build_row.html
