Metadata-Version: 1.0
Name: zumanji
Version: 0.3.7.1
Summary: A web interface for aggregating results from nose-performance
Home-page: https://github.com/disqus/zumanji
Author: DISQUS
Author-email: opensource@disqus.com
License: Apache License 2.0
Platform: UNKNOWN
Classifier: Framework :: Django
Classifier: Intended Audience :: Developers
Classifier: Intended Audience :: System Administrators
Classifier: Operating System :: OS Independent
Classifier: Topic :: Software Development
